pii_sdk/__init__.py
pii_sdk/errors.py
pii_sdk/pii_sdk.py
pii_sdk/pii_sdk_config.py
pii_sdk/py.typed
pii_sdk/types/__init__.py
pii_sdk/types/api_ogranization.py
pii_sdk/types/api_user.py
pii_sdk/types/enums/__init__.py
pii_sdk/types/enums/organization_user_state.py
pii_sdk/utils/__init__.py
pii_sdk/utils/internal_api_error_handler.py
ul_pii_sdk-4.2.8.dist-info/METADATA
ul_pii_sdk-4.2.8.dist-info/WHEEL
ul_pii_sdk-4.2.8.dist-info/top_level.txt
ul_pii_sdk-4.2.8.dist-info/RECORD
