Metadata-Version: 2.1
Name: ul_pii_sdk
Version: 4.2.8
Summary: Pii sdk
Author: Unic-lab
License: MIT
Platform: any
Classifier: Intended Audience :: Developers
Classifier: License :: OSI Approved :: MIT License
Classifier: Programming Language :: Python
Classifier: Programming Language :: Python :: 3.6
Classifier: Programming Language :: Python :: 3.7
Classifier: Programming Language :: Python :: 3.8
Classifier: Programming Language :: Python :: 3.9
Classifier: Operating System :: OS Independent
Requires-Dist: ul-api-utils >=7.2.8
Requires-Dist: ul-data-aggregator-sdk >=10.1.7
